DffPIPO_CE.sv
module DffPIPO_CE(
    input CE,
    input [7:0] D,
    input clk,
    input nReset,

    output reg [7:0] Q
);

always @(posedge clk ) begin
    if(nReset) begin
        if(CE==1)
            Q <= D;
    end
    else 
        Q <= 8'h00;
end
endmodule

Regs.sv
module Reg_CY(
input CE,
input CY_in,
input clk,

output logic CY_out
);

always @(posedge clk ) begin
    if(CE==1)
        CY_out <= CY_in;
end
endmodule


module Aku(
    input CE,
    input [7:0] D,
    input clk,
    input nReset,

    output reg [7:0] Q
);

always @(posedge clk ) begin
    if(nReset) begin
        if(CE==1)
            Q <= D;
    end
    else 
        Q <= 8'h00;
end
endmodule

defines.sv
//ALU
`define ADD 3'd0
`define SUB 3'd1
`define AND 3'd2
`define OR  3'd3
`define XOR 3'd4
`define NOT 3'd5
`define LD  3'd6
`define ST  3'd7

ALU.sv
`include "defines.sv"

module ALU
(input [2:0] ALUCode,
 input [7:0] A, //Aku
 input [7:0] R, //Reg
 input Ci,
 
 output logic Co,
 output logic [7:0] out
 
);

always @(*) begin
    case (ALUCode)
        `ALU_ADD: begin //ADD
            {Co,out} = A + R + Ci;
        end

        `ALU_SUB: begin //SUB
            {Co,out} = A - R - Ci;
        end

        `ALU_AND: begin //AND
            out = A & R;
            Co = 0;
        end

        `ALU_OR: begin //OR
            out = A | R;
            Co = 0;                
        end

        `ALU_XOR: begin //XOR
            out = A ^ R;
            Co = 0;   
        end
        `ALU_NOT: begin //NOT
            out = ~A;
            Co = 0;
        end
        `ALU_LD: begin //LD
            out = R;
            Co = 0;
        end
        default:
        begin
            out = 0;
            Co = 0;
        end
    endcase
end
endmodule

ALU_tb.sv
`timescale  1ns/1ps

`include "Regs.sv"
`include "ALU.sv"
`include "DffPIPO_CE.sv" 

module ALU_tb;

//Regs
logic A_CE_tb = 0;
logic CY_CE_tb = 0;
logic clk_tb = 0;
logic nReset = 1;


//ALU
logic [2:0] ALUCode_tb;
logic [7:0] R_tb = 8'd4;
logic Ci_tb = 0;
logic [7:0] out_tb;

//WIRES
wire ALU_2_RegCY;
wire [7:0] ALU_2_RegAku;
wire [7:0] RegAku_2_ALU;

//=========================== MODULES ==========================

ALU ALU_1(
.ALUCode(ALUCode_tb),
.A(RegAku_2_ALU),
.R(R_tb),
.Ci(Ci_tb), 
.Co(ALU_2_RegCY),
.out(ALU_2_RegAku)
);

Reg_CY Reg_CY_1(
.CE(CY_CE_tb),
.CY_in(ALU_2_RegCY),
.clk(clk_tb)
);

DffPIPO_CE Aku(
.CE(A_CE_tb),
.D(ALU_2_RegAku),
.clk(clk_tb),
.Q(RegAku_2_ALU),
.nReset(nReset)
);


// ====================================================== TB ======================================

initial begin //clk
forever begin
    #5 clk_tb = ~clk_tb;
end
end

initial begin //start values
A_CE_tb = 1;
CY_CE_tb = 1;
clk_tb = 0;

nReset = 0;
#6 nReset = 1;

#200 $finish;
end


initial begin // ALU Codes
    ALUCode_tb = `ADD;
    #10 
    #10 
    #10 ALUCode_tb = `SUB;
    #10 ALUCode_tb = `ADD;
    #10 ALUCode_tb = `AND;
    #10 ALUCode_tb = `OR;
    #10 ALUCode_tb = `ADD;
    #10 ALUCode_tb = `XOR;
    #10 ALUCode_tb = `NOT;
    #10 ALUCode_tb = `LD;
    #10 ALUCode_tb = `SUB;
    #10 ALUCode_tb = `ADD;
    #10 ALUCode_tb = `ADD;
    #10 ALUCode_tb = `SUB;
    #10 ALUCode_tb = `NOT;
    #10 ALUCode_tb = `ADD;
end







initial begin
    $dumpfile("ALU_tb.vcd");
    $dumpvars;
    $dumpon;
end
endmodule

ALU_tb.vcd
$date
	Wed Nov  6 15:24:12 2024
$end
$version
	Icarus Verilog
$end
$timescale
	1ps
$end
$scope module ALU_tb $end
$var wire 8 ! RegAku_2_ALU [7:0] $end
$var wire 1 " ALU_2_RegCY $end
$var wire 8 # ALU_2_RegAku [7:0] $end
$var reg 3 $ ALUCode_tb [2:0] $end
$var reg 1 % A_CE_tb $end
$var reg 1 & CY_CE_tb $end
$var reg 1 ' Ci_tb $end
$var reg 8 ( R_tb [7:0] $end
$var reg 1 ) clk_tb $end
$var reg 1 * nReset $end
$scope module ALU_1 $end
$var wire 3 + ALUCode [2:0] $end
$var wire 1 ' Ci $end
$var wire 8 , R [7:0] $end
$var wire 8 - A [7:0] $end
$var reg 1 " Co $end
$var reg 8 . out [7:0] $end
$upscope $end
$scope module Aku $end
$var wire 1 % CE $end
$var wire 8 / D [7:0] $end
$var wire 1 ) clk $end
$var wire 1 * nReset $end
$var reg 8 0 Q [7:0] $end
$upscope $end
$scope module Reg_CY_1 $end
$var wire 1 & CE $end
$var wire 1 " CY_in $end
$var wire 1 ) clk $end
$var reg 1 1 CY_out $end
$upscope $end
$upscope $end
$enddefinitions $end
#0
$dumpvars
x1
bx 0
bx /
bx .
bx -
b100 ,
b0 +
0*
0)
b100 (
0'
1&
1%
b0 $
bx #
x"
bx !
$end
#5000
0"
b100 #
b100 .
b100 /
b0 !
b0 -
b0 0
1)
#6000
1*
#10000
0)
#15000
b1000 #
b1000 .
b1000 /
b100 !
b100 -
b100 0
01
1)
#20000
0)
#25000
b1100 #
b1100 .
b1100 /
b1000 !
b1000 -
b1000 0
1)
#30000
b100 #
b100 .
b100 /
0)
b1 $
b1 +
#35000
b0 #
b0 .
b0 /
b100 !
b100 -
b100 0
1)
#40000
b1000 #
b1000 .
b1000 /
0)
b0 $
b0 +
#45000
b1100 #
b1100 .
b1100 /
b1000 !
b1000 -
b1000 0
1)
#50000
b0 #
b0 .
b0 /
0)
b10 $
b10 +
#55000
b0 !
b0 -
b0 0
1)
#60000
b100 #
b100 .
b100 /
0)
b11 $
b11 +
#65000
b100 !
b100 -
b100 0
1)
#70000
b1000 #
b1000 .
b1000 /
0)
b0 $
b0 +
#75000
b1100 #
b1100 .
b1100 /
b1000 !
b1000 -
b1000 0
1)
#80000
0)
b100 $
b100 +
#85000
b1000 #
b1000 .
b1000 /
b1100 !
b1100 -
b1100 0
1)
#90000
b11110011 #
b11110011 .
b11110011 /
0)
b101 $
b101 +
#95000
b1100 #
b1100 .
b1100 /
b11110011 !
b11110011 -
b11110011 0
1)
#100000
b100 #
b100 .
b100 /
0)
b110 $
b110 +
#105000
b100 !
b100 -
b100 0
1)
#110000
b0 #
b0 .
b0 /
0)
b1 $
b1 +
#115000
1"
b11111100 #
b11111100 .
b11111100 /
b0 !
b0 -
b0 0
1)
#120000
0"
b100 #
b100 .
b100 /
0)
b0 $
b0 +
#125000
b1000 #
b1000 .
b1000 /
b100 !
b100 -
b100 0
1)
#130000
0)
#135000
b1100 #
b1100 .
b1100 /
b1000 !
b1000 -
b1000 0
1)
#140000
b100 #
b100 .
b100 /
0)
b1 $
b1 +
#145000
b0 #
b0 .
b0 /
b100 !
b100 -
b100 0
1)
#150000
b11111011 #
b11111011 .
b11111011 /
0)
b101 $
b101 +
#155000
b100 #
b100 .
b100 /
b11111011 !
b11111011 -
b11111011 0
1)
#160000
b11111111 #
b11111111 .
b11111111 /
0)
b0 $
b0 +
#165000
1"
b11 #
b11 .
b11 /
b11111111 !
b11111111 -
b11111111 0
1)
#170000
0)
#175000
0"
b111 #
b111 .
b111 /
b11 !
b11 -
b11 0
11
1)
#180000
0)
#185000
b1011 #
b1011 .
b1011 /
01
b111 !
b111 -
b111 0
1)
#190000
0)
#195000
b1111 #
b1111 .
b1111 /
b1011 !
b1011 -
b1011 0
1)
#200000
0)
#205000
b10011 #
b10011 .
b10011 /
b1111 !
b1111 -
b1111 0
1)
