Regs.sv
module Reg_CY(
input CE,
input CY_in,
input clk,

output logic CY_out
);

always @(posedge clk ) begin
    if(CE==1)
        CY_out <= CY_in;
end
endmodule


module Aku(
    input CE,
    input [7:0] D,
    input clk,
    input nReset,

    output reg [7:0] Q
);

always @(posedge clk ) begin
    if(nReset) begin
        if(CE==1)
            Q <= D;
    end
    else 
        Q <= 8'h00;
end
endmodule

defines.sv
//ALU
`define ADD 3'd0
`define SUB 3'd1
`define AND 3'd2
`define OR  3'd3
`define XOR 3'd4
`define NOT 3'd5
`define LD  3'd6
`define ST  3'd7

ALU.sv
`include "defines.sv"

module ALU
(input [2:0] ALUCode,
 input [7:0] A, //Aku
 input [7:0] R, //Reg
 input Ci,
 
 output logic Co,
 output logic [7:0] out
 
);

always @(*) begin
    case (ALUCode)
        `ALU_ADD: begin //ADD
            {Co,out} = A + R + Ci;
        end

        `ALU_SUB: begin //SUB
            {Co,out} = A - R - Ci;
        end

        `ALU_AND: begin //AND
            out = A & R;
            Co = 0;
        end

        `ALU_OR: begin //OR
            out = A | R;
            Co = 0;                
        end

        `ALU_XOR: begin //XOR
            out = A ^ R;
            Co = 0;   
        end
        `ALU_NOT: begin //NOT
            out = ~A;
            Co = 0;
        end
        `ALU_LD: begin //LD
            out = R;
            Co = 0;
        end
        default:
        begin
            out = 0;
            Co = 0;
        end
    endcase
end
endmodule

ALU_tb.sv
`timescale  1ns/1ps

`include "Regs.sv"
`include "ALU.sv" 

module ALU_tb;

//Regs
logic A_CE_tb = 0;
logic CY_CE_tb = 0;
logic clk_tb = 0;
logic nReset = 1;


//ALU
logic [2:0] ALUCode_tb;
logic [7:0] A_tb = 8'd8;
logic [7:0] R_tb = 8'd4;
logic Ci_tb = 0;
logic Co_tb = 0;
logic [7:0] out_tb;

//WIRES
wire ALU_2_RegCY;
wire [7:0] ALU_2_RegAku;
wire [7:0] RegAku_2_ALU;

//=========================== MODULES ==========================

ALU ALU_1(
.ALUCode(ALUCode_tb),
.A(RegAku_2_ALU),
.R(R_tb),
.Ci(Ci_tb), 
.Co(ALU_2_RegCY),
.out(ALU_2_RegAku)
);

Reg_CY Reg_CY_1(
.CE(CY_CE_tb),
.CY_in(ALU_2_RegCY),
.clk(clk_tb)
);

Aku Aku_1(
.CE(A_CE_tb),
.D(ALU_2_RegAku),
.clk(clk_tb),
.Q(RegAku_2_ALU),
.nReset(nReset)
);


initial begin
A_CE_tb = 1;
CY_CE_tb = 1;
clk_tb = 0;

nReset = 0;
#6 nReset = 1;

#100 $finish;
end

initial begin
forever begin
    #5 clk_tb = ~clk_tb;
end
end

initial begin
    #1 ALUCode_tb = 3'd0;
    #10
    #10 ALUCode_tb = 3'd1;
    #10 ALUCode_tb = 3'd0;
end

initial begin
    $dumpfile("ALU_tb.vcd");
    $dumpvars;
    $dumpon;
end




endmodule

ALU_tb.vcd
$date
	Mon Oct 28 14:54:47 2024
$end
$version
	Icarus Verilog
$end
$timescale
	1ps
$end
$scope module ALU_tb $end
$var wire 8 ! RegAku_2_ALU [7:0] $end
$var wire 1 " ALU_2_RegCY $end
$var wire 8 # ALU_2_RegAku [7:0] $end
$var reg 3 $ ALUCode_tb [2:0] $end
$var reg 1 % A_CE_tb $end
$var reg 8 & A_tb [7:0] $end
$var reg 1 ' CY_CE_tb $end
$var reg 1 ( Ci_tb $end
$var reg 1 ) Co_tb $end
$var reg 8 * R_tb [7:0] $end
$var reg 1 + clk_tb $end
$var reg 1 , nReset $end
$scope module ALU_1 $end
$var wire 3 - ALUCode [2:0] $end
$var wire 1 ( Ci $end
$var wire 8 . R [7:0] $end
$var wire 8 / A [7:0] $end
$var reg 1 " Co $end
$var reg 8 0 out [7:0] $end
$upscope $end
$scope module Aku_1 $end
$var wire 1 % CE $end
$var wire 8 1 D [7:0] $end
$var wire 1 + clk $end
$var wire 1 , nReset $end
$var reg 8 2 Q [7:0] $end
$upscope $end
$scope module Reg_CY_1 $end
$var wire 1 ' CE $end
$var wire 1 " CY_in $end
$var wire 1 + clk $end
$var reg 1 3 CY_out $end
$upscope $end
$upscope $end
$enddefinitions $end
#0
$dumpvars
x3
bx 2
bx 1
bx 0
bx /
b100 .
bx -
0,
0+
b100 *
0)
0(
1'
b1000 &
1%
bx $
bx #
x"
bx !
$end
#1000
b0 $
b0 -
#5000
0"
b100 #
b100 0
b100 1
b0 !
b0 /
b0 2
1+
#6000
1,
#10000
0+
#15000
b1000 #
b1000 0
b1000 1
b100 !
b100 /
b100 2
03
1+
#20000
0+
#21000
b0 #
b0 0
b0 1
b1 $
b1 -
#25000
1"
b11111100 #
b11111100 0
b11111100 1
b0 !
b0 /
b0 2
1+
#30000
0+
#31000
0"
b100 #
b100 0
b100 1
b0 $
b0 -
#35000
b1000 #
b1000 0
b1000 1
b100 !
b100 /
b100 2
1+
#40000
0+
#45000
b1100 #
b1100 0
b1100 1
b1000 !
b1000 /
b1000 2
1+
#50000
0+
#55000
b10000 #
b10000 0
b10000 1
b1100 !
b1100 /
b1100 2
1+
#60000
0+
#65000
b10100 #
b10100 0
b10100 1
b10000 !
b10000 /
b10000 2
1+
#70000
0+
#75000
b11000 #
b11000 0
b11000 1
b10100 !
b10100 /
b10100 2
1+
#80000
0+
#85000
b11100 #
b11100 0
b11100 1
b11000 !
b11000 /
b11000 2
1+
#90000
0+
#95000
b100000 #
b100000 0
b100000 1
b11100 !
b11100 /
b11100 2
1+
#100000
0+
#105000
b100100 #
b100100 0
b100100 1
b100000 !
b100000 /
b100000 2
1+
