DffPIPO_CE.sv
module DffPIPO_CE(
    input CE,
    input [7:0] D,
    input clk,
    input nReset,

    output reg [7:0] Q
);

always @(posedge clk ) begin
    if(nReset) begin
        if(CE==1)
            Q <= D;
    end
    else 
        Q <= 8'h00;
end
endmodule

DffPIPO_CE_SET.sv
module DffPIPO_CE_SET #(parameter SET = 0, parameter SIZE = 8)(
    input CE,
    input [SIZE-1:0] D,
    input clk,
    input nReset,

    output reg [SIZE-1:0] Q
);

always @(posedge clk ) begin
    if(nReset) begin
        if(CE==1)
            Q <= D;
    end
    else 
        Q <= SET;
end
endmodule

RegisterFile.sv
`timescale  1ns/1ps

module RegfisterFile(
    input [7:0] A,
    input clk,
    input nReset,
    input [3:0] RegNum, //decoder will be placed in ID
    input RegCE,

    output logic [7:0] out);

wire [7:0] Reg2Mult [0:3];

DffPIPO_CE_SET R0(
.D(A),
.CE(RegNum[0] & RegCE),
.clk(clk),
.nReset(nReset),
.Q(Reg2Mult[0])
);

DffPIPO_CE_SET #(.SET(1)) R1(
.D(A),
.CE(RegNum[1] & RegCE),
.clk(clk),
.nReset(nReset),
.Q(Reg2Mult[1])
);

DffPIPO_CE_SET #(.SET(2)) R2(
.D(A),
.CE(RegNum[2] & RegCE),
.clk(clk),
.nReset(nReset),
.Q(Reg2Mult[2])
);

DffPIPO_CE_SET #(.SET(4)) R3(
.D(A),
.CE(RegNum[3] & RegCE),
.clk(clk),
.nReset(nReset),
.Q(Reg2Mult[3])
);


always @(*) begin
    case (RegNum)
        4'd1: out = Reg2Mult[0];
        4'd2: out = Reg2Mult[1];
        4'd4: out = Reg2Mult[2];
        4'd8: out = Reg2Mult[3];
        default: out = 4'h0;
    endcase
end

endmodule

RegisterFile_tb.sv
`timescale  1ns/1ps

`include "RegisterFile.sv"
`include "DffPIPO_CE.sv"

module RegisterFile_tb;

logic [7:0] A_tb;
logic clk_tb;
logic nReset_tb;
logic [7:0] out_tb;
logic [3:0] RegNum_tb;
logic CE;

//=========================== MODULES ==========================


RegfisterFile RegfisterFile_1(
.A(A_tb),
.clk(clk_tb),
.RegCE(CE),
.RegNum(RegNum_tb),
.nReset(nReset_tb),
.out(out_tb)
);

// ====================================================== TB ======================================

initial begin //clk
forever begin
    #5 clk_tb = ~clk_tb;
end
end

initial begin //start values
clk_tb = 0;
nReset_tb = 0;
#6 nReset_tb = 1;

#60 $finish;
end


initial begin // 
    CE = 1'b1;
    #10 RegNum_tb = 4'b0001; A_tb = 8'd4;
    #10 RegNum_tb = 4'b0010; A_tb = 8'd5;
    #10 RegNum_tb = 4'b0100; A_tb = 8'd6;
    #10 RegNum_tb = 4'b1000; A_tb = 8'd7;
    #10 RegNum_tb = 4'b0000;
end

initial begin
    $dumpfile("RegisterFile_tb.vcd");
    $dumpvars;
    $dumpon;
end




endmodule

RegisterFile_tb.vcd
$date
	Thu Nov  7 15:46:10 2024
$end
$version
	Icarus Verilog
$end
$timescale
	1ps
$end
$scope module RegisterFile_tb $end
$var wire 8 ! out_tb [7:0] $end
$var reg 8 " A_tb [7:0] $end
$var reg 1 # CE $end
$var reg 4 $ RegNum_tb [3:0] $end
$var reg 1 % clk_tb $end
$var reg 1 & nReset_tb $end
$scope module RegfisterFile_1 $end
$var wire 8 ' A [7:0] $end
$var wire 1 # RegCE $end
$var wire 4 ( RegNum [3:0] $end
$var wire 1 % clk $end
$var wire 1 & nReset $end
$var reg 8 ) out [7:0] $end
$scope module R0 $end
$var wire 1 * CE $end
$var wire 8 + D [7:0] $end
$var wire 1 % clk $end
$var wire 1 & nReset $end
$var parameter 32 , SET $end
$var reg 8 - Q [7:0] $end
$upscope $end
$scope module R1 $end
$var wire 1 . CE $end
$var wire 8 / D [7:0] $end
$var wire 1 % clk $end
$var wire 1 & nReset $end
$var parameter 32 0 SET $end
$var reg 8 1 Q [7:0] $end
$upscope $end
$scope module R2 $end
$var wire 1 2 CE $end
$var wire 8 3 D [7:0] $end
$var wire 1 % clk $end
$var wire 1 & nReset $end
$var parameter 32 4 SET $end
$var reg 8 5 Q [7:0] $end
$upscope $end
$scope module R3 $end
$var wire 1 6 CE $end
$var wire 8 7 D [7:0] $end
$var wire 1 % clk $end
$var wire 1 & nReset $end
$var parameter 32 8 SET $end
$var reg 8 9 Q [7:0] $end
$upscope $end
$upscope $end
$upscope $end
$enddefinitions $end
$comment Show the parameter values. $end
$dumpall
b100 8
b10 4
b1 0
b0 ,
$end
#0
$dumpvars
bx 9
bx 7
x6
bx 5
bx 3
x2
bx 1
bx /
x.
bx -
bx +
x*
bx )
bx (
bx '
0&
0%
bx $
1#
bx "
bx !
$end
#5000
b0 !
b0 )
b0 -
b1 1
b10 5
b100 9
1%
#6000
1&
#10000
1*
0.
02
06
0%
b100 "
b100 '
b100 +
b100 /
b100 3
b100 7
b1 $
b1 (
#15000
b100 !
b100 )
b100 -
1%
#20000
0*
1.
b1 !
b1 )
0%
b101 "
b101 '
b101 +
b101 /
b101 3
b101 7
b10 $
b10 (
#25000
b101 !
b101 )
b101 1
1%
#30000
0.
12
b10 !
b10 )
0%
b110 "
b110 '
b110 +
b110 /
b110 3
b110 7
b100 $
b100 (
#35000
b110 !
b110 )
b110 5
1%
#40000
02
16
b100 !
b100 )
0%
b111 "
b111 '
b111 +
b111 /
b111 3
b111 7
b1000 $
b1000 (
#45000
b111 !
b111 )
b111 9
1%
#50000
06
b0 !
b0 )
0%
b0 $
b0 (
