DffPIPO_CE.sv
module DffPIPO_CE(
    input CE,
    input [7:0] D,
    input clk,
    input nReset,

    output reg [7:0] Q
);

always @(posedge clk ) begin
    if(nReset) begin
        if(CE==1)
            Q <= D;
    end
    else 
        Q <= 8'h00;
end
endmodule

RegisterFile.sv
`timescale  1ns/1ps

`include "Regs.sv"
`include "ALU.sv" 

module RegfisterFile(
    input [7:0] Aku,
    input clk,
    input nReset,
    input [3:0] RegX, //decoder will be placed in ID
    input RegCE,

    output logic [7:0] out);

wire [7:0] Reg2Mult [0:3];

DffPIPO_CE R0(
.D(Aku),
.CE(RegX[0] & RegCE),
.clk(clk),
.nReset(nReset),
.Q(Reg2Mult[0])
);

DffPIPO_CE R1(
.D(Aku),
.CE(RegX[1] & RegCE),
.clk(clk),
.nReset(nReset),
.Q(Reg2Mult[1])
);

DffPIPO_CE R2(
.D(Aku),
.CE(RegX[2] & RegCE),
.clk(clk),
.nReset(nReset),
.Q(Reg2Mult[2])
);

DffPIPO_CE R3(
.D(Aku),
.CE(RegX[3] & RegCE),
.clk(clk),
.nReset(nReset),
.Q(Reg2Mult[3])
);


always @(*) begin
    case (RegX)
        4'd1: out = Reg2Mult[0];
        4'd2: out = Reg2Mult[1];
        4'd4: out = Reg2Mult[2];
        4'd8: out = Reg2Mult[3];
        default: out = 4'h0;
    endcase
end


endmodule

RegisterFile_tb.sv
`timescale  1ns/1ps

`include "RegisterFile.sv"
`include "DffPIPO_CE.sv"

module RegisterFile_tb;

logic [7:0] Aku_tb;
logic clk_tb;
logic nReset_tb;
logic [7:0] out_tb;
logic [3:0] RegX_tb;
logic CE;

//=========================== MODULES ==========================


RegfisterFile RegfisterFile_1(
.Aku(Aku_tb),
.clk(clk_tb),
.RegCE(CE),
.RegX(RegX_tb),
.nReset(nReset_tb),
.out(out_tb)
);

// ====================================================== TB ======================================

initial begin //clk
forever begin
    #5 clk_tb = ~clk_tb;
end
end

initial begin //start values
clk_tb = 0;
nReset_tb = 0;
#6 nReset_tb = 1;

#60 $finish;
end


initial begin // 
    CE = 1'b1;
    #10 RegX_tb = 4'b0001; Aku_tb = 8'd4;
    #10 RegX_tb = 4'b0010; Aku_tb = 8'd5;
    #10 RegX_tb = 4'b0100; Aku_tb = 8'd6;
    #10 RegX_tb = 4'b1000; Aku_tb = 8'd7;
    #10 RegX_tb = 4'b0000;
end

initial begin
    $dumpfile("RegisterFile_tb.vcd");
    $dumpvars;
    $dumpon;
end




endmodule

Regs.sv
module Reg_CY(
input CE,
input CY_in,
input clk,

output logic CY_out
);

always @(posedge clk ) begin
    if(CE==1)
        CY_out <= CY_in;
end
endmodule

defines.sv
//ALU
`define ADD 3'd0
`define SUB 3'd1
`define AND 3'd2
`define OR  3'd3
`define XOR 3'd4
`define NOT 3'd5
`define LD  3'd6

ALU.sv
`include "defines.sv"

module ALU
(input [2:0] ALUCode,
 input [7:0] A, //Aku
 input [7:0] R, //Reg
 input Ci,
 
 output logic Co,
 output logic [7:0] out
 
);

always @(*) begin
    case (ALUCode)
        `ADD: begin //ADD
            {Co,out} = A + R + Ci;
        end

        `SUB: begin //SUB
            {Co,out} = A - R - Ci;
        end

        `AND: begin //AND
            out = A & R;
            Co = 0;
        end

        `OR: begin //OR
            out = A | R;
            Co = 0;                
        end

        `XOR: begin //XOR
            out = A ^ R;
            Co = 0;   
        end
        `NOT: begin //NOT
            out = ~A;
            Co = 0;
        end
        `LD: begin //LD
            out = R;
            Co = 0;
        end
    endcase
end
endmodule

RegisterFile_tb.vcd
$date
	Mon Nov  4 14:52:21 2024
$end
$version
	Icarus Verilog
$end
$timescale
	1ps
$end
$scope module ALU $end
$var wire 8 ! A [7:0] $end
$var wire 3 " ALUCode [2:0] $end
$var wire 1 # Ci $end
$var wire 8 $ R [7:0] $end
$var reg 1 % Co $end
$var reg 8 & out [7:0] $end
$upscope $end
$scope module Reg_CY $end
$var wire 1 ' CE $end
$var wire 1 ( CY_in $end
$var wire 1 ) clk $end
$var reg 1 * CY_out $end
$upscope $end
$scope module RegisterFile_tb $end
$var wire 8 + out_tb [7:0] $end
$var reg 8 , Aku_tb [7:0] $end
$var reg 1 - CE $end
$var reg 4 . RegX_tb [3:0] $end
$var reg 1 / clk_tb $end
$var reg 1 0 nReset_tb $end
$scope module RegfisterFile_1 $end
$var wire 8 1 Aku [7:0] $end
$var wire 1 - RegCE $end
$var wire 4 2 RegX [3:0] $end
$var wire 1 / clk $end
$var wire 1 0 nReset $end
$var reg 8 3 out [7:0] $end
$scope module R0 $end
$var wire 1 4 CE $end
$var wire 8 5 D [7:0] $end
$var wire 1 / clk $end
$var wire 1 0 nReset $end
$var reg 8 6 Q [7:0] $end
$upscope $end
$scope module R1 $end
$var wire 1 7 CE $end
$var wire 8 8 D [7:0] $end
$var wire 1 / clk $end
$var wire 1 0 nReset $end
$var reg 8 9 Q [7:0] $end
$upscope $end
$scope module R2 $end
$var wire 1 : CE $end
$var wire 8 ; D [7:0] $end
$var wire 1 / clk $end
$var wire 1 0 nReset $end
$var reg 8 < Q [7:0] $end
$upscope $end
$scope module R3 $end
$var wire 1 = CE $end
$var wire 8 > D [7:0] $end
$var wire 1 / clk $end
$var wire 1 0 nReset $end
$var reg 8 ? Q [7:0] $end
$upscope $end
$upscope $end
$upscope $end
$enddefinitions $end
#0
$dumpvars
bx ?
bx >
x=
bx <
bx ;
x:
bx 9
bx 8
x7
bx 6
bx 5
x4
bx 3
bx 2
bx 1
00
0/
bx .
1-
bx ,
bx +
x*
z)
z(
z'
bx &
x%
bz $
z#
bz "
bz !
$end
#5000
b0 +
b0 3
b0 6
b0 9
b0 <
b0 ?
1/
#6000
10
#10000
14
07
0:
0=
0/
b100 ,
b100 1
b100 5
b100 8
b100 ;
b100 >
b1 .
b1 2
#15000
b100 +
b100 3
b100 6
1/
#20000
04
17
b0 +
b0 3
0/
b101 ,
b101 1
b101 5
b101 8
b101 ;
b101 >
b10 .
b10 2
#25000
b101 +
b101 3
b101 9
1/
#30000
07
1:
b0 +
b0 3
0/
b110 ,
b110 1
b110 5
b110 8
b110 ;
b110 >
b100 .
b100 2
#35000
b110 +
b110 3
b110 <
1/
#40000
0:
1=
b0 +
b0 3
0/
b111 ,
b111 1
b111 5
b111 8
b111 ;
b111 >
b1000 .
b1000 2
#45000
b111 +
b111 3
b111 ?
1/
#50000
0=
b0 +
b0 3
0/
b0 .
b0 2
