defines.sv
//ALU
`define ADD 3'd0
`define SUB 3'd1
`define AND 3'd2
`define OR  3'd3
`define XOR 3'd4
`define NOT 3'd5
`define LD  3'd6
`define ST  3'd7

ProgramCounter.sv
/* WHAT IS THIS? 
// This module is a Program Counter
// It increments itself every clock cycle
// It outputs the counter value on output  

// The outputed value of counter can be updated by JMP instruction.
*/

`include "defines.sv"

module ProgramCounter(
input WriteEnable,          //Write enable - disables/enables overwriting counter - allows/disables jumps 
input clk,                  
input nReset,
input  logic [5:0] AddrIn,  // Address to which PC will jump, if WE is enabled
output logic [5:0] AddrOut  // Outputs current value of PC's counter
);



always @(posedge clk) begin
    //check for reset or JMP signal. AddrIn == 0 holds AddrOut at 0, so there is no error when JMPing to AddrIn = 0;
    if(nReset==0 || (WriteEnable==1 && AddrIn == 6'd0))
        AddrOut = 6'd0;
    else begin
        if (WriteEnable==1)
            AddrOut = AddrIn;
        else
            AddrOut = AddrOut + 1;
    end   
end

endmodule

PC_tb.sv
/* WHAT IS THIS? 
 This is a Testbench that tests Program Counter
*/
`define tb_path "tb_files/PC_tb.vcd"
`timescale 1ns/1ps

`include "ProgramCounter.sv"


module PC_tb;

logic clk_tb;
logic nReset_tb;
logic WriteEnable_tb;
logic [5:0] AddrIn_tb;
logic [5:0] AddrOut_tb;

ProgramCounter PC(
.WriteEnable(WriteEnable_tb),
.clk(clk_tb),
.nReset(nReset_tb),
.AddrIn(AddrIn_tb),
.AddrOut(AddrOut_tb)
);

initial begin //clk
forever begin
    #5 clk_tb = ~clk_tb;
end
end


initial begin // start values
clk_tb = 0;
nReset_tb = 0;
#6 nReset_tb = 1;

#250 $finish;
end






initial begin
WriteEnable_tb = 1'b0;
AddrIn_tb = 6'd22;

#100 WriteEnable_tb = 1;  AddrIn_tb = 6'd0;
#10 WriteEnable_tb = 0;  AddrIn_tb = 6'd55;
#30 WriteEnable_tb = 1;  AddrIn_tb = 6'd26;
#10 WriteEnable_tb = 0;  AddrIn_tb = 6'd55;

end









initial begin // file save
    $dumpfile(`tb_path);
    $dumpvars;
    $dumpon;
end


endmodule

sim_files/PC_tb.vcd
$date
	Thu Dec 19 18:25:41 2024
$end
$version
	Icarus Verilog
$end
$timescale
	1ps
$end
$scope module PC_tb $end
$var wire 6 ! AddrOut_tb [5:0] $end
$var reg 6 " AddrIn_tb [5:0] $end
$var reg 1 # WriteEnable_tb $end
$var reg 1 $ clk_tb $end
$var reg 1 % nReset_tb $end
$scope module PC $end
$var wire 6 & AddrIn [5:0] $end
$var wire 1 # WriteEnable $end
$var wire 1 $ clk $end
$var wire 1 % nReset $end
$var reg 6 ' AddrOut [5:0] $end
$upscope $end
$upscope $end
$enddefinitions $end
$comment Show the parameter values. $end
$dumpall
$end
#0
$dumpvars
bx '
b10110 &
0%
0$
0#
b10110 "
bx !
$end
#5000
b0 !
b0 '
1$
#6000
1%
#10000
0$
#15000
b1 !
b1 '
1$
#20000
0$
#25000
b10 !
b10 '
1$
#30000
0$
#35000
b11 !
b11 '
1$
#40000
0$
#45000
b100 !
b100 '
1$
#50000
0$
#55000
b101 !
b101 '
1$
#60000
0$
#65000
b110 !
b110 '
1$
#70000
0$
#75000
b111 !
b111 '
1$
#80000
0$
#85000
b1000 !
b1000 '
1$
#90000
0$
#95000
b1001 !
b1001 '
1$
#100000
0$
b0 "
b0 &
1#
#105000
b0 !
b0 '
1$
#110000
0$
b110111 "
b110111 &
0#
#115000
b1 !
b1 '
1$
#120000
0$
#125000
b10 !
b10 '
1$
#130000
0$
#135000
b11 !
b11 '
1$
#140000
0$
b11010 "
b11010 &
1#
#145000
b11010 !
b11010 '
1$
#150000
0$
b110111 "
b110111 &
0#
#155000
b11011 !
b11011 '
1$
#160000
0$
#165000
b11100 !
b11100 '
1$
#170000
0$
#175000
b11101 !
b11101 '
1$
#180000
0$
#185000
b11110 !
b11110 '
1$
#190000
0$
#195000
b11111 !
b11111 '
1$
#200000
0$
#205000
b100000 !
b100000 '
1$
#210000
0$
#215000
b100001 !
b100001 '
1$
#220000
0$
#225000
b100010 !
b100010 '
1$
#230000
0$
#235000
b100011 !
b100011 '
1$
#240000
0$
#245000
b100100 !
b100100 '
1$
#250000
0$
#255000
b100101 !
b100101 '
1$
