DebugModule.sv
/* WHAT IS THIS? 
// This module is a mofied version of Program Memory
// It loads instructions in binary from a file generated by a custom made assembler.
// 
*/
module DebugModule #(parameter INS_ADDR_WIDTH, parameter MEM_WIDTH, parameter MEM_LEN)(
    input [INS_ADDR_WIDTH-1:0] addr,
    input [MEM_WIDTH-1:0] accuValue,
    input clk,
    output logic isAccuValueCorrect,  
    output logic [MEM_WIDTH-1:0] correctValueAccu
 );
    
    reg [5:0] delayQaddr; 
    reg [5:0] delayDaddr;
   
    localparam accuValueCheckFilePath = "Assembler/accuCheckValues.hex";
    integer i=0;
    reg [MEM_WIDTH-1:0] Mem  [MEM_LEN-1:0];

     
    initial begin 
        //memory initialisation
        for(i=0; i<MEM_LEN; i=i+1) begin
            Mem[i] = {MEM_WIDTH{1'bx}};
        end

        //loading correctValueAccu
        $readmemh(accuValueCheckFilePath, Mem,0, MEM_LEN-1);

    end
    

    //delay output of correct value by cycle but with usage of a too slow clock
    //that is why negedge is added. Two edges per one cycle is needed
    //Otherwise PC does not meet hold requirements, then delayQaddr grabs every second one addr.
    always_ff @(negedge clk) begin
        delayDaddr = addr;
    end
    always_ff @(posedge clk) begin
        delayQaddr = delayDaddr;
    end

    assign correctValueAccu = Mem[delayQaddr];
    assign isAccuValueCorrect = (correctValueAccu == accuValue) ? 1'b1 : 1'b0;

endmodule

DffPIPO_CE_SET.sv
module DffPIPO_CE_SET #(parameter SET = 0, parameter SIZE = 8)(
    input CE,
    input [SIZE-1:0] D,
    input clk,
    input nReset,

    output reg [SIZE-1:0] Q
);

always @(posedge clk ) begin
    if(nReset) begin
        if(CE==1)
            Q <= D;
    end
    else 
        Q <= SET;
end
endmodule

defines.sv
//ALU
`define ADD 3'd0
`define SUB 3'd1
`define AND 3'd2
`define OR  3'd3
`define XOR 3'd4
`define NOT 3'd5
`define LD  3'd6
`define ST  3'd7

ALU.sv
/* WHAT IS THIS? 
// This module is an Arithmetic Logic Unit
// It calculates results of most of the instructions.
// The output directly feeds the Accumulator
// It has 7 operations and 1 default case.                                                                                                                                                                                                                                                                                                                                                                                                                                                                                                                                                                                    
*/

`include "defines.sv"

module ALU
(input [2:0] ALUCode,           // ALUCode provided by InsDec - selects proper operation described in Instruction
 input [7:0] AccuIn,            // Data from Accumulator output
 input [7:0] DataIn,            // Data from Secondary output (RegisterFile / Immediate / DataMemory)
 input Ci,                      // Carry In - used in overflow/underflow cases of ADD/SUB operations
 
 output logic Co,               // Carry Out - signalises whether overflow/underflow occured during ADD/SUB operations
 output logic [7:0] DataOut     // Outputs result of ALU operation
 
);

always @(*) begin
    case (ALUCode)
        `ALU_ADD: begin //0. ADD
            {Co,DataOut} = AccuIn + DataIn + Ci;
        end

        `ALU_SUB: begin //1. SUB
            {Co,DataOut} = AccuIn - DataIn - Ci;
        end

        `ALU_AND: begin //2. AND
            DataOut = AccuIn & DataIn;
            Co = 0;
        end

        `ALU_OR: begin //3. OR
            DataOut = AccuIn | DataIn;
            Co = 0;                
        end

        `ALU_XOR: begin //4. XOR
            DataOut = AccuIn ^ DataIn;
            Co = 0;   
        end
        `ALU_NOT: begin //5. NOT
            DataOut = ~AccuIn;
            Co = 0;
        end
        `ALU_LD: begin //6. LD
            DataOut = DataIn;
            Co = 0;
        end
        default:      //any other but in practise 7
        begin
            DataOut = 0;
            Co = 0;
        end
    endcase
end
endmodule

SmallModules.sv
module Multiplexer4to1 #(parameter DataWidth = 8)(
input [DataWidth-1:0] inA,
input [DataWidth-1:0] inB,
input [DataWidth-1:0] inC,
input [DataWidth-1:0] inD,
input [1:0] SelDataSource,
output logic [DataWidth-1:0] out
);

always @(*) begin
    case(SelDataSource)
        0: assign out = inA;
        1: assign out = inB;
        2: assign out = inC;
        3: assign out = inD;
    endcase
end
endmodule

DataMemory.sv
/* WHAT IS THIS? 
// This module is an Data Memory
// It stores DATA_LEN of Registers of DATA_WIDTH width that hold values just like Accumulator.                                                                                                                                                                                                                                                                                                                                                                                                                                                                                                                                                                                    
*/


module DataMemory  #(parameter DATA_WIDTH = 8, parameter DATA_LEN = 256)(
    input [DATA_WIDTH-1:0] Accu,            // Inputs Accumulator's output
    input WriteEnable,                      // Enables/Disables writing into memory
    input [DATA_WIDTH-1:0] Addr,            // Address on which basis proper memory cell is chosen
    input nReset,
    input clk,
    output reg [DATA_WIDTH-1:0] DataOut     // Outputs data of DM cell of "Addr" number 
);

reg [DATA_WIDTH-1:0] DataMem [DATA_LEN-1:0];

integer i=0;
always @(clk) 
begin
    if(nReset==0) begin             //RESET

        for(i=0; i<DATA_LEN; i=i+1) begin
            DataMem[i] = i;
        end

    end else begin                  //Normal Operations
              
        if(WriteEnable==1) begin    // Write

            DataMem[Addr] = Accu;

        end else begin              // Read
            DataMem[Addr] = DataMem[Addr];


        end

    end
end

always @(*) begin //I wonder what synthesis will discover.
                
    if(WriteEnable==1)
        DataOut = 8'b0;
    else
        DataOut = DataMem[Addr];
end
endmodule

RegisterFile.sv
/* WHAT IS THIS? 
// This module is a Register File
// It contain 4x8bit Registers (Dff) or 3x8bit  
// Output is a multiplexed register output                                                                                                                                                                                                                                                                                                                                                                                                                                                                                                                                                                                         
*/

`timescale  1ns/1ps
`include "DffPIPO_CE_SET.sv"

module RegfisterFile(
    input [7:0] Accu,   // inputs Accumulator output
    input clk,          
    input nReset,
    input [3:0] RegNum, // decoder will be placed in ID
    input RegCE,        // Clock Enable/Write Enable that allows for writing into registers
    input [7:0] inR3,   // input that allows to insert an user-defined value

    output logic [7:0] out);

wire [7:0] Reg2Mult [0:3];

DffPIPO_CE_SET R0(
.D(Accu),
.CE(RegNum[0] & RegCE),
.clk(clk),
.nReset(nReset),
.Q(Reg2Mult[0])
);

DffPIPO_CE_SET #(.SET(1)) R1(
.D(Accu),
.CE(RegNum[1] & RegCE),
.clk(clk),
.nReset(nReset),
.Q(Reg2Mult[1])
);

DffPIPO_CE_SET #(.SET(2)) R2(
.D(Accu),
.CE(RegNum[2] & RegCE),
.clk(clk),
.nReset(nReset),
.Q(Reg2Mult[2])
);

assign Reg2Mult[3] = inR3; //it can be done differently, this one is the fastest to ipmlement

// DffPIPO_CE_SET #(.SET(4)) R3(
// .D(Accu),
// .CE(RegNum[3] & RegCE),
// .clk(clk),
// .nReset(nReset),
// .Q(Reg2Mult[3])
// );


always @(*) begin
    case (RegNum)
        4'd1: out = Reg2Mult[0];
        4'd2: out = Reg2Mult[1];
        4'd4: out = Reg2Mult[2];
        4'd8: out = Reg2Mult[3];
        default: out = 4'h0;
    endcase
end

endmodule

InstructionDecoder.sv
/* WHAT IS THIS? 
// This module is an Instruction Decoder
// It decodes instruction fetched from program memory                                                                                                                                                                                                                                                                                                                                                                                                                                                                                                                                                                                         
*/

module InstructionDecoder(
input [12:0] Ins,                   //Instruction from Program Memory

output logic DataMem_WE,            // Write Enable for Data Mem (//shouldnt all CE be WE?)
output logic Reg_CE,                // Registers Write Enable Signal
output logic [3:0] RegAddr,         // Decoded Register address
output logic [7:0] Data,            // Data comming out of Instruction
output logic [1:0] SelDataSource,   // Selector of Data Source that will go into the ALU

output logic [2:0] ALUCode,         // ALU Operation Code 
output logic Carry_CE,              // Carry Write Enable

output logic Accu_CE,               // Accumulator Write Enable

output logic [6:0] ControlPC        // Flag (MSB) + Jump-to-Addrres (6b) :: Program Counter position manipulation
);

parameter InsWidth = `PM_ID_INS_WIDTH;

// Wires created for easier access to Instruction
wire [4:0] OpCode_w;        // The OpCode of instruction - 5 bits
wire [1:0] OpCodeSection_w; // The OpCode section of instruction - there are 4 sections: Register, DataMem, ImmediateData, Rest
wire [2:0] OpCodeRest_w;    // Opcode without OpCodeSection - so the REST 3 bits of OpCode
wire [1:0] RNum_w;          // Register Number - overlaps with Data_w
wire [7:0] Data_w;          // Data part of instruction - 8 bits
wire [5:0] PCAddrIn;        // Input address of Program Counter pointing to the jump address. First 6 LSB of Data_w (overlaps) 

assign OpCode_w        = Ins[InsWidth-1 : InsWidth-5];         //5 first five MSB bits
assign OpCodeSection_w = Ins[InsWidth-1 : InsWidth-2];         //2 first two MSB bits
assign OpCodeRest_w    = Ins[InsWidth-3 : InsWidth-5];         //3 3-5 MSB bits
assign RNum_w          = Ins[1:0];         //2 1-2 LSB bit
assign Data_w          = Ins[7:0];
assign PCAddrIn        = Ins[5:0];

always @(*) begin

//RegAddr
    case (RNum_w)
     0: RegAddr = 4'b0001;
     1: RegAddr = 4'b0010;
     2: RegAddr = 4'b0100;
     3: RegAddr = 4'b1000;
     default: RegAddr = 4'b0000;
    endcase 

//Reg_CE 
    Reg_CE = (OpCode_w == `OPCODE_ST_R) ? 1 : 0;

//SelDataSource 
    if(OpCodeSection_w!=`SEC_REST) begin
        SelDataSource = OpCodeSection_w;
    end else begin
        case(OpCodeRest_w)
            0: SelDataSource = `SEC_R;      // LD_R
            1: SelDataSource = `SEC_DM;     // LD_MD
            2: SelDataSource = `SEC_IMD;    // LD_IMD
            3: SelDataSource = `SEC_DM;      // ST_R
            4: SelDataSource = `SEC_R;     // ST_DM
            default: SelDataSource = `SEC_R; //Arbitrary choice
        endcase
    end
     


//ALUCode and Accu_CE 
    if(OpCodeSection_w != `SEC_REST) begin   //First 3 instructions sections (0-7,8-15,16-23)
        if(OpCodeRest_w<=`ALU_XOR) begin
            ALUCode = OpCodeRest_w;
            Accu_CE = 1;
        end else begin
            ALUCode = `ALU_DEF;
            Accu_CE = 0;
        end
    end else begin              //Last instructions section (24-31)

        case(OpCodeRest_w)
            0,1,2:   begin ALUCode =  `ALU_LD;  Accu_CE = 1; end //Load  instructions
            5:       begin ALUCode =  `ALU_NOT; Accu_CE = 1; end //Not   instruction
            default: begin ALUCode =  `ALU_DEF; Accu_CE = 0; end
        endcase

    end


//Carry_CE 
    Carry_CE = (OpCodeSection_w != `SEC_REST && OpCodeRest_w <= `ALU_SUB) ? 1 : 0;  //Every ADD-SUB instruction

//DataMem_WE 
    DataMem_WE = (OpCode_w == `OPCODE_ST_DM) ? 1 : 0; //Only on Store

//ControlPC 
    ControlPC = (OpCodeSection_w != `SEC_REST && OpCodeRest_w == `JMP) ? {1'b1, PCAddrIn} : {7'd0}; //Sets jump flag and address on JMP instruction; otherwise sends zeroes

end

//Data: IMD / DM_Addr
assign Data = Data_w;

endmodule

ProgramMemory.sv
/* WHAT IS THIS? 
// This module is a Program Memory
// It loads instructions in binary from a file generated by a custom made assembler.
// Then it pushes the instructions to the memory of this module.                                                                                                                                                                                                                                                                                                                                                                                                                                                                                                                                                                                         
*/

module ProgramMemory (
    input [5:0] addr,
    output reg [12:0] InsOut
);

localparam insFilePath = "Assembler/InsBin.asm";

integer i=0;
reg [12:0] Mem  [63:0];

//memory initialisation 
initial begin 
    for(i=0; i<=63; i=i+1) begin
        Mem[i] = {`OPCODE_NOP,8'bxxxx_xxxx};
    end

//loading instructions
$readmemb(insFilePath, Mem,0,63);
end 

assign InsOut = Mem[addr];

endmodule

ProgramCounter.sv
/* WHAT IS THIS? 
// This module is a Program Counter
// It increments itself every clock cycle
// It outputs the counter value on output  

// The outputed value of counter can be updated by JMP instruction.
*/

`include "defines.sv"

module ProgramCounter(
input WriteEnable,          //Write enable - disables/enables overwriting counter - allows/disables jumps 
input clk,                  
input nReset,
input  logic [5:0] AddrIn,  // Address to which PC will jump, if WE is enabled
output logic [5:0] AddrOut  // Outputs current value of PC's counter
);



always @(posedge clk) begin
    //check for reset or JMP signal. AddrIn == 0 holds AddrOut at 0, so there is no error when JMPing to AddrIn = 0;
    if(nReset==0 || (WriteEnable==1 && AddrIn == 6'd0))
        AddrOut = 6'd0;
    else begin
        if (WriteEnable==1)
            AddrOut = AddrIn;
        else
            AddrOut = AddrOut + 1;
    end   
end

endmodule

top.sv
/* WHAT IS THIS? 
 This is a module that connects all modules
*/

`include "ProgramCounter.sv"
`include "ProgramMemory.sv"
`include "InstructionDecoder.sv"
`include "ALU.sv"
`include "RegisterFile.sv"
`include "SmallModules.sv"
`include "DataMemory.sv"

`include "DebugModule.sv"
module top(input clk, input nReset,
input  [7:0] inR3,          //user-defined input to one of regs 
output [5:0] PC_Addr_o,     //debug
output [7:0] Accu_out_o);   //debug

//============================================================================
//----------------------------------- WIRES ----------------------------------
//============================================================================

// PC outputs
wire [5:0] PC_Addr;

// PM outputs
wire [12:0] PM_Ins;

// ID outputs
wire ID_DataMem_WE;
wire ID_RegCE;
wire [3:0] ID_RegAddr;
wire [7:0] ID_Data;
wire [1:0] ID_SelDataSource;  
wire [2:0] ID_ALUCode; 
wire ID_Carry_CE;
wire ID_Accu_CE;
wire [6:0] ID_ControlPC;


// ---------------------------- Second Part -----------------------------------

// RF outputs
wire [7:0] RegFile_2_Mult;

// Data Memory outputs
wire [7:0] DataMem_2_Mult;

// Multiplexer output
wire [7:0] Mult_2_ALU;

//ALU output
wire [7:0] ALU_2_Accu;
wire ALU_Co;

//Carry output
wire RegCarry_2_ALU;

//Accu output
wire [7:0] Accu_out;

//============================================================================
//++++++++++++++++++++++++++++++++++ MODULES +++++++++++++++++++++++++++++++++
//============================================================================


//PROGRAM COUNTER
ProgramCounter PC(
.WriteEnable(ID_ControlPC[6]),
.clk(clk),
.nReset(nReset),
.AddrIn(ID_ControlPC[5:0]),
.AddrOut(PC_Addr)
);

//PROGRAM MEMORY
ProgramMemory PM(.addr(PC_Addr), .InsOut(PM_Ins));

//INSTRUCTION DECODER
InstructionDecoder ID(
.Ins(PM_Ins),          //input 
.DataMem_WE(ID_DataMem_WE),
.RegAddr(ID_RegAddr),  //outputs
.Data(ID_Data),
.SelDataSource(ID_SelDataSource),
.ALUCode(ID_ALUCode), 
.Reg_CE(ID_RegCE),
.Carry_CE(ID_Carry_CE),
.Accu_CE(ID_Accu_CE),
.ControlPC(ID_ControlPC)
);

// ---------------------------- Second Part -----------------------------------


//REGISTER FILE
RegfisterFile RF(
.RegCE(ID_RegCE),  //inputs
.RegNum(ID_RegAddr),
.Accu(Accu_out),
.nReset(nReset),
.clk(clk),
.inR3(inR3),
.out(RegFile_2_Mult) //output
);

//DATA MEMORY
DataMemory DM(
.Accu(Accu_out),
.WriteEnable(ID_DataMem_WE),
.Addr(ID_Data),
.nReset(nReset),
.clk(clk),
.DataOut(DataMem_2_Mult)
);

// MULTIPLEXER
Multiplexer4to1 Mult4to1(
.inA(RegFile_2_Mult),
.inB(DataMem_2_Mult),
.inC(ID_Data),
.inD(8'b0),
.SelDataSource(ID_SelDataSource),
.out(Mult_2_ALU)
);

//ALU
ALU ALU_1(
.ALUCode(ID_ALUCode), //inputs
.DataIn(Mult_2_ALU),
.AccuIn(Accu_out),
.Ci(RegCarry_2_ALU), 
.Co(ALU_Co), //outputs
.DataOut(ALU_2_Accu)
);

//CARRY
DffPIPO_CE_SET #(.SIZE(1)) RegCY(
.CE(ID_Carry_CE), //inputs
.D(ALU_Co),
.clk(clk),
.nReset(nReset & ID_Carry_CE),
.Q(RegCarry_2_ALU) //output
);

//ACCUMULATOR
DffPIPO_CE_SET A(
.CE(ID_Accu_CE), //inputs
.D(ALU_2_Accu),
.clk(clk),
.nReset(nReset),
.Q(Accu_out) //output
);


assign PC_Addr_o = PC_Addr;
assign Accu_out_o = Accu_out;
endmodule

top_tb.sv
/* WHAT IS THIS? 
 This is a Testbench that tests all modules
*/

`define tb_path "sim_files/top_tb.vcd"

`timescale  1ns/1ps

`include "top.sv"

module top_tb;

logic clk_tb;
logic nReset_tb;
logic [7:0] inR3_reg;
logic [5:0] PC_Addr_wire;
logic [7:0] Accu_out_wire;

 

top top1(.clk(clk_tb),.nReset(nReset_tb),
.inR3(inR3_reg), 
.PC_Addr_o(PC_Addr_wire),       //debug 
.Accu_out_o(Accu_out_wire));    //debug


// ---------------------------- DEBUG Part -----------------------------------
DebugModule #(.INS_ADDR_WIDTH(6), .MEM_WIDTH(8), .MEM_LEN(64)) DebMod_CheckAccuVal (
.addr(PC_Addr_wire),
.accuValue(Accu_out_wire),
.clk(clk_tb)
);



//============================================================================
//****************************** INPUT SIGNALS *******************************
//============================================================================

always @(*) begin
    case(PC_Addr_wire)
        6'd45:  inR3_reg = 8'd85; //0x55 //0b0101_0101  //LD to accu // A=85
        6'd46:  inR3_reg = 8'hF0;                       //AND        // A=80
        6'd47:  inR3_reg = 8'hF0;                       //OR         // A=240
        6'd48:  inR3_reg = 8'h0F;                       //ADD        // A=255
        6'd49:  inR3_reg = 8'hFF;                       //SUB        // A=0
        default inR3_reg = 8'hx1;
    endcase
end



//============================================================================
//******************************** SIMULATION ********************************
//============================================================================

initial begin //clk
forever begin
    #5 clk_tb = ~clk_tb;
end
end

initial begin // start values
clk_tb = 0;
nReset_tb = 0;
#6 nReset_tb = 1;

#1000 $finish;
end

initial begin // file save
    $dumpfile(`tb_path);
    $dumpvars;
    $dumpon;
end


endmodule

sim_files/top_tb.vcd
$date
	Fri Feb 14 14:56:08 2025
$end
$version
	Icarus Verilog
$end
$timescale
	1ps
$end
$scope module top_tb $end
$var wire 6 ! PC_Addr_wire [5:0] $end
$var wire 8 " Accu_out_wire [7:0] $end
$var reg 1 # clk_tb $end
$var reg 8 $ inR3_reg [7:0] $end
$var reg 1 % nReset_tb $end
$scope module DebMod_CheckAccuVal $end
$var wire 1 # clk $end
$var wire 8 & correctValueAccu [7:0] $end
$var wire 1 ' isAccuValueCorrect $end
$var wire 6 ( addr [5:0] $end
$var wire 8 ) accuValue [7:0] $end
$var parameter 32 * INS_ADDR_WIDTH $end
$var parameter 32 + MEM_LEN $end
$var parameter 32 , MEM_WIDTH $end
$var parameter 232 - accuValueCheckFilePath $end
$var reg 6 . delayDaddr [5:0] $end
$var reg 6 / delayQaddr [5:0] $end
$var integer 32 0 i [31:0] $end
$upscope $end
$scope module top1 $end
$var wire 8 1 Accu_out_o [7:0] $end
$var wire 6 2 PC_Addr_o [5:0] $end
$var wire 1 # clk $end
$var wire 8 3 inR3 [7:0] $end
$var wire 1 % nReset $end
$var wire 8 4 RegFile_2_Mult [7:0] $end
$var wire 1 5 RegCarry_2_ALU $end
$var wire 13 6 PM_Ins [12:0] $end
$var wire 6 7 PC_Addr [5:0] $end
$var wire 8 8 Mult_2_ALU [7:0] $end
$var wire 2 9 ID_SelDataSource [1:0] $end
$var wire 1 : ID_RegCE $end
$var wire 4 ; ID_RegAddr [3:0] $end
$var wire 1 < ID_DataMem_WE $end
$var wire 8 = ID_Data [7:0] $end
$var wire 7 > ID_ControlPC [6:0] $end
$var wire 1 ? ID_Carry_CE $end
$var wire 1 @ ID_Accu_CE $end
$var wire 3 A ID_ALUCode [2:0] $end
$var wire 8 B DataMem_2_Mult [7:0] $end
$var wire 8 C Accu_out [7:0] $end
$var wire 1 D ALU_Co $end
$var wire 8 E ALU_2_Accu [7:0] $end
$scope module A $end
$var wire 1 # clk $end
$var wire 1 % nReset $end
$var wire 8 F D [7:0] $end
$var wire 1 @ CE $end
$var parameter 32 G SET $end
$var parameter 32 H SIZE $end
$var reg 8 I Q [7:0] $end
$upscope $end
$scope module ALU_1 $end
$var wire 8 J AccuIn [7:0] $end
$var wire 8 K DataIn [7:0] $end
$var wire 1 5 Ci $end
$var wire 3 L ALUCode [2:0] $end
$var reg 1 D Co $end
$var reg 8 M DataOut [7:0] $end
$upscope $end
$scope module DM $end
$var wire 8 N Accu [7:0] $end
$var wire 8 O DataOut [7:0] $end
$var wire 1 # clk $end
$var wire 1 % nReset $end
$var wire 1 < WriteEnable $end
$var wire 8 P Addr [7:0] $end
$var parameter 32 Q DATA_LEN $end
$var parameter 32 R DATA_WIDTH $end
$var integer 32 S i [31:0] $end
$upscope $end
$scope module ID $end
$var wire 8 T Data [7:0] $end
$var wire 2 U RNum_w [1:0] $end
$var wire 6 V PCAddrIn [5:0] $end
$var wire 5 W OpCode_w [4:0] $end
$var wire 2 X OpCodeSection_w [1:0] $end
$var wire 3 Y OpCodeRest_w [2:0] $end
$var wire 13 Z Ins [12:0] $end
$var wire 8 [ Data_w [7:0] $end
$var parameter 32 \ InsWidth $end
$var reg 3 ] ALUCode [2:0] $end
$var reg 1 @ Accu_CE $end
$var reg 1 ? Carry_CE $end
$var reg 7 ^ ControlPC [6:0] $end
$var reg 1 < DataMem_WE $end
$var reg 4 _ RegAddr [3:0] $end
$var reg 1 : Reg_CE $end
$var reg 2 ` SelDataSource [1:0] $end
$upscope $end
$scope module Mult4to1 $end
$var wire 2 a SelDataSource [1:0] $end
$var wire 8 b inB [7:0] $end
$var wire 8 c inC [7:0] $end
$var wire 8 d inD [7:0] $end
$var wire 8 e inA [7:0] $end
$var parameter 32 f DataWidth $end
$var reg 8 g out [7:0] $end
$upscope $end
$scope module PC $end
$var wire 6 h AddrIn [5:0] $end
$var wire 1 i WriteEnable $end
$var wire 1 # clk $end
$var wire 1 % nReset $end
$var reg 6 j AddrOut [5:0] $end
$upscope $end
$scope module PM $end
$var wire 13 k InsOut [12:0] $end
$var wire 6 l addr [5:0] $end
$var parameter 160 m insFilePath $end
$var integer 32 n i [31:0] $end
$upscope $end
$scope module RF $end
$var wire 8 o Accu [7:0] $end
$var wire 1 : RegCE $end
$var wire 4 p RegNum [3:0] $end
$var wire 1 # clk $end
$var wire 8 q inR3 [7:0] $end
$var wire 1 % nReset $end
$var reg 8 r out [7:0] $end
$scope module R0 $end
$var wire 1 s CE $end
$var wire 8 t D [7:0] $end
$var wire 1 # clk $end
$var wire 1 % nReset $end
$var parameter 32 u SET $end
$var parameter 32 v SIZE $end
$var reg 8 w Q [7:0] $end
$upscope $end
$scope module R1 $end
$var wire 1 x CE $end
$var wire 8 y D [7:0] $end
$var wire 1 # clk $end
$var wire 1 % nReset $end
$var parameter 32 z SET $end
$var parameter 32 { SIZE $end
$var reg 8 | Q [7:0] $end
$upscope $end
$scope module R2 $end
$var wire 1 } CE $end
$var wire 8 ~ D [7:0] $end
$var wire 1 # clk $end
$var wire 1 % nReset $end
$var parameter 32 !" SET $end
$var parameter 32 "" SIZE $end
$var reg 8 #" Q [7:0] $end
$upscope $end
$upscope $end
$scope module RegCY $end
$var wire 1 ? CE $end
$var wire 1 D D $end
$var wire 1 # clk $end
$var wire 1 $" nReset $end
$var parameter 32 %" SET $end
$var parameter 32 &" SIZE $end
$var reg 1 5 Q $end
$upscope $end
$upscope $end
$upscope $end
$enddefinitions $end
$comment Show the parameter values. $end
$dumpall
b1 &"
b0 %"
b1000 ""
b10 !"
b1000 {
b1 z
b1000 v
b0 u
b100000101110011011100110110010101101101011000100110110001100101011100100010111101001001011011100111001101000010011010010110111000101110011000010111001101101101 m
b1000 f
b1101 \
b1000 R
b100000000 Q
b1000 H
b0 G
b100000101110011011100110110010101101101011000100110110001100101011100100010111101100001011000110110001101110101010000110110100001100101011000110110101101010110011000010110110001110101011001010111001100101110011010000110010101111000 -
b1000 ,
b1000000 +
b110 *
$end
#0
$dumpvars
0$"
bx #"
bx ~
x}
bx |
bx y
xx
bx w
bx t
xs
bx r
bx q
bx p
bx o
b1000000 n
bx l
bx k
bx j
xi
bx h
bx g
bx e
b0 d
bx c
bx b
bx a
bx `
bx _
bx ^
bx ]
bx [
bx Z
bx Y
bx X
bx W
bx V
bx U
bx T
b100000000 S
bx P
bx O
bx N
bx M
bx L
bx K
bx J
bx I
bx F
bx E
xD
bx C
bx B
bx A
x@
x?
bx >
bx =
x<
bx ;
x:
bx 9
bx 8
bx 7
bx 6
x5
bx 4
bx 3
bx 2
bx 1
b1000000 0
bx /
bx .
bx )
bx (
x'
bx &
0%
bx $
0#
bx "
bx !
$end
#5000
0D
b1 E
b1 F
b1 M
b0 w
b1 |
b10 #"
05
b0 "
b0 )
b0 1
b0 C
b0 I
b0 J
b0 N
b0 o
b0 t
b0 y
b0 ~
b0 h
0i
0s
0x
0}
b1 8
b1 K
b1 g
b0 >
b0 ^
0<
1?
1@
b0 A
b0 L
b0 ]
b0 9
b0 `
b0 a
0:
b10 ;
b10 _
b10 p
b1 4
b1 e
b1 r
b1 V
b11111110 B
b11111110 O
b11111110 b
b1 =
b1 P
b1 T
b1 c
b1 [
b1 U
b0 Y
b0 X
b0 W
bx0001 $
bx0001 3
bx0001 q
b1 6
b1 Z
b1 k
b0 !
b0 (
b0 2
b0 7
b0 j
b0 l
b100000000 S
1#
#6000
1$"
1%
#10000
b0 .
0#
#15000
b1 "
b1 )
b1 1
b1 C
b1 I
b1 J
b1 N
b1 o
b1 t
b1 y
b1 ~
0D
b0 E
b0 F
b0 M
b1 A
b1 L
b1 ]
1'
b1 Y
b1 W
b1 &
b0 /
b100000001 6
b100000001 Z
b100000001 k
b1 !
b1 (
b1 2
b1 7
b1 j
b1 l
1#
#20000
b1 .
0#
#25000
1D
b11111111 E
b11111111 F
b11111111 M
b0 "
b0 )
b0 1
b0 C
b0 I
b0 J
b0 N
b0 o
b0 t
b0 y
b0 ~
1'
b10 !
b10 (
b10 2
b10 7
b10 j
b10 l
b0 &
b1 /
1#
#30000
b10 .
0#
#35000
0D
b11111101 E
b11111101 F
b11111101 M
b11111111 "
b11111111 )
b11111111 1
b11111111 C
b11111111 I
b11111111 J
b11111111 N
b11111111 o
b11111111 t
b11111111 y
b11111111 ~
15
1'
b11111111 &
b10 /
b11 !
b11 (
b11 2
b11 7
b11 j
b11 l
1#
#40000
b11 .
0#
#45000
05
b11111101 "
b11111101 )
b11111101 1
b11111101 C
b11111101 I
b11111101 J
b11111101 N
b11111101 o
b11111101 t
b11111101 y
b11111101 ~
0D
b11111111 E
b11111111 F
b11111111 M
b10 8
b10 K
b10 g
b10 4
b10 e
b10 r
b0 A
b0 L
b0 ]
b100 ;
b100 _
b100 p
b10 V
b11111101 B
b11111101 O
b11111101 b
b10 =
b10 P
b10 T
b10 c
b10 [
b10 U
b0 Y
b0 W
1'
b10 6
b10 Z
b10 k
b100 !
b100 (
b100 2
b100 7
b100 j
b100 l
b11111101 &
b11 /
1#
#50000
b100 .
0#
#55000
1D
b1 E
b1 F
b1 M
b11111111 "
b11111111 )
b11111111 1
b11111111 C
b11111111 I
b11111111 J
b11111111 N
b11111111 o
b11111111 t
b11111111 y
b11111111 ~
1'
b11111111 &
b100 /
b101 !
b101 (
b101 2
b101 7
b101 j
b101 l
1#
#60000
b101 .
0#
#65000
0D
b100 E
b100 F
b100 M
15
b1 "
b1 )
b1 1
b1 C
b1 I
b1 J
b1 N
b1 o
b1 t
b1 y
b1 ~
1'
b110 !
b110 (
b110 2
b110 7
b110 j
b110 l
b1 &
b101 /
1#
#70000
b110 .
0#
#75000
b110 E
b110 F
b110 M
b100 "
b100 )
b100 1
b100 C
b100 I
b100 J
b100 N
b100 o
b100 t
b100 y
b100 ~
05
1'
b100 &
b110 /
b111 !
b111 (
b111 2
b111 7
b111 j
b111 l
1#
#80000
b111 .
0#
#85000
b110 "
b110 )
b110 1
b110 C
b110 I
b110 J
b110 N
b110 o
b110 t
b110 y
b110 ~
0$"
b0 E
b0 F
b0 M
1s
b0 8
b0 K
b0 g
b0 4
b0 e
b0 r
0?
0@
b111 A
b111 L
b111 ]
1:
b1 ;
b1 _
b1 p
b0 V
b11111111 B
b11111111 O
b11111111 b
b0 =
b0 P
b0 T
b0 c
b0 [
b0 U
b100 Y
b11 X
b11100 W
1'
b1110000000000 6
b1110000000000 Z
b1110000000000 k
b1000 !
b1000 (
b1000 2
b1000 7
b1000 j
b1000 l
b110 &
b111 /
1#
#90000
b1000 .
0#
#95000
b110 8
b110 K
b110 g
b110 4
b110 e
b110 r
b110 w
1$"
b1100 E
b1100 F
b1100 M
0s
1?
1@
b0 A
b0 L
b0 ]
0:
b0 Y
b0 X
b0 W
b1000 /
b0 6
b0 Z
b0 k
b1001 !
b1001 (
b1001 2
b1001 7
b1001 j
b1001 l
1#
#100000
b1001 .
0#
#105000
b1100 "
b1100 )
b1100 1
b1100 C
b1100 I
b1100 J
b1100 N
b1100 o
b1100 t
b1100 y
b1100 ~
b1110 E
b1110 F
b1110 M
b10 8
b10 K
b10 g
b10 4
b10 e
b10 r
b100 ;
b100 _
b100 p
b10 V
b11111101 B
b11111101 O
b11111101 b
b10 =
b10 P
b10 T
b10 c
b10 [
b10 U
1'
b10 6
b10 Z
b10 k
b1010 !
b1010 (
b1010 2
b1010 7
b1010 j
b1010 l
b1100 &
b1001 /
1#
#110000
b1010 .
0#
#115000
b1110 "
b1110 )
b1110 1
b1110 C
b1110 I
b1110 J
b1110 N
b1110 o
b1110 t
b1110 y
b1110 ~
0$"
b110 E
b110 F
b110 M
b110 8
b110 K
b110 g
b110 4
b110 e
b110 r
0?
b10 A
b10 L
b10 ]
b1 ;
b1 _
b1 p
1'
b0 V
b11111111 B
b11111111 O
b11111111 b
b0 =
b0 P
b0 T
b0 c
b0 [
b0 U
b10 Y
b10 W
b1110 &
b1010 /
b1000000000 6
b1000000000 Z
b1000000000 k
b1011 !
b1011 (
b1011 2
b1011 7
b1011 j
b1011 l
1#
#120000
b1011 .
0#
#125000
b110 "
b110 )
b110 1
b110 C
b110 I
b110 J
b110 N
b110 o
b110 t
b110 y
b110 ~
b11111001 E
b11111001 F
b11111001 M
b101 A
b101 L
b101 ]
b101 Y
b11 X
b11101 W
1'
b1110100000000 6
b1110100000000 Z
b1110100000000 k
b1100 !
b1100 (
b1100 2
b1100 7
b1100 j
b1100 l
b110 &
b1011 /
1#
#130000
b1100 .
0#
#135000
b11111001 "
b11111001 )
b11111001 1
b11111001 C
b11111001 I
b11111001 J
b11111001 N
b11111001 o
b11111001 t
b11111001 y
b11111001 ~
b11111111 E
b11111111 F
b11111111 M
b11 A
b11 L
b11 ]
1'
b11 Y
b0 X
b11 W
b11111001 &
b1100 /
b1100000000 6
b1100000000 Z
b1100000000 k
b1101 !
b1101 (
b1101 2
b1101 7
b1101 j
b1101 l
1#
#140000
b1101 .
0#
